{
    "AX": {
        "error": 0.005559702357400044,
        "error_type": "SEM",
        "filter_outliers_dict": {
            "filter_outliers": true,
            "iterations": 1,
            "std_devs": 2
        },
        "fit": "Average",
        "value": 0.017215340986286375
    },
    "CDD": {
        "error": 5.6111052899543644e-05,
        "error_type": "SEM",
        "filter_outliers_dict": {
            "filter_outliers": false,
            "iterations": 1,
            "std_devs": 2
        },
        "fit": "Average",
        "value": 0.0009721178103134253
    },
    "H1": {
        "error": 0.01919649027019451,
        "error_type": "SEM",
        "filter_outliers_dict": {
            "filter_outliers": true,
            "iterations": 1,
            "std_devs": 2
        },
        "fit": "Average",
        "value": -0.0531313550388323
    },
    "L1": {
        "error": 0.007040228529788327,
        "error_type": "SEM",
        "filter_outliers_dict": {
            "filter_outliers": true,
            "iterations": 1,
            "std_devs": 2
        },
        "fit": "Average",
        "value": -9.729551501173128e-05
    },
    "L2": {
        "error": 0.0069128528551258535,
        "error_type": "SEM",
        "filter_outliers_dict": {
            "filter_outliers": false,
            "iterations": 1,
            "std_devs": 2
        },
        "fit": "Average",
        "value": 0.0010350505776599037
    }
}